<?xml version="1.0" ?><annotation>
	<folder/>
	<filename>750.jpg</filename>
	<path>750.jpg</path>
	<source>
		<database>roboflow.com</database>
	</source>
	<size>
		<width>1280</width>
		<height>720</height>
		<depth>3</depth>
	</size>
	<segmented>0</segmented>
	<object>
		<name>sanhaco_do_coqueiro</name>
		<pose>Unspecified</pose>
		<truncated>0</truncated>
		<difficult>0</difficult>
		<occluded>0</occluded>
		<bndbox>
			<xmin>591</xmin>
			<xmax>941</xmax>
			<ymin>252</ymin>
			<ymax>411</ymax>
		</bndbox>
	</object>
	<object>
		<name>chupim</name>
		<pose>Unspecified</pose>
		<truncated>0</truncated>
		<difficult>0</difficult>
		<occluded>0</occluded>
		<bndbox>
			<xmin>357</xmin>
			<xmax>874</xmax>
			<ymin>341</ymin>
			<ymax>647</ymax>
		</bndbox>
	</object>
	<object>
		<name>chupim</name>
		<pose>Unspecified</pose>
		<truncated>0</truncated>
		<difficult>0</difficult>
		<occluded>0</occluded>
		<bndbox>
			<xmin>3</xmin>
			<xmax>245</xmax>
			<ymin>423</ymin>
			<ymax>716</ymax>
		</bndbox>
	</object>
	<object>
		<name>chupim</name>
		<pose>Unspecified</pose>
		<truncated>0</truncated>
		<difficult>0</difficult>
		<occluded>0</occluded>
		<bndbox>
			<xmin>778</xmin>
			<xmax>1019</xmax>
			<ymin>401</ymin>
			<ymax>716</ymax>
		</bndbox>
	</object>
	<object>
		<name>chupim</name>
		<pose>Unspecified</pose>
		<truncated>0</truncated>
		<difficult>0</difficult>
		<occluded>0</occluded>
		<bndbox>
			<xmin>422</xmin>
			<xmax>654</xmax>
			<ymin>564</ymin>
			<ymax>713</ymax>
		</bndbox>
	</object>
	<object>
		<name>chupim</name>
		<pose>Unspecified</pose>
		<truncated>0</truncated>
		<difficult>0</difficult>
		<occluded>0</occluded>
		<bndbox>
			<xmin>326</xmin>
			<xmax>539</xmax>
			<ymin>283</ymin>
			<ymax>488</ymax>
		</bndbox>
	</object>
</annotation>